[{"s": "amortizator-dlya-stiralnoj-mashiny-lg-120n", "t": "Амортизатор LG 120N: характеристики, замена и выбор", "i": "🔧", "c": "remont-stiralnykh-mashin"}, {"s": "amortizator-dlya-stiralnoj-mashiny-whirlpool", "t": "Амортизатор для стиральной машины Whirlpool: выбор и замена", "i": "🔧", "c": "remont-stiralnykh-mashin"}, {"s": "amortizator-dlya-stiralnoj-mashiny-elektrolyuks", "t": "Амортизатор для стиральной машины Электролюкс: выбор и замена", "i": "🔧", "c": "remont-stiralnykh-mashin"}, {"s": "amortizatory-dlya-stiralnykh-mashin-bosch", "t": "Амортизаторы для стиральных машин Bosch: выбор и замена", "i": "🔧", "c": "remont-stiralnykh-mashin"}, {"s": "amortizator-dlya-stiralnoj-mashiny-lg-4901er2001e", "t": "Амортизатор LG 4901ER2001E: ремонт, замена, проверка", "i": "🔧", "c": "remont-stiralnykh-mashin"}, {"s": "amortizator-dlya-stiralnoj-mashiny-samsung-s803j", "t": "Амортизатор для стиральной машины Samsung S803J: замена и выбор", "i": "🔧", "c": "remont-stiralnykh-mashin"}, {"s": "amortizatory-dlya-stiralnoj-mashiny-bosch-maxx-6", "t": "Амортизаторы для Bosch Maxx 6: замена и выбор", "i": "🔧", "c": "remont-stiralnykh-mashin"}, {"s": "amortizatory-dlya-stiralnoj-mashiny-lg-s-pryamym-privodom", "t": "Амортизаторы для стиральной машины LG с прямым приводом: выбор и замена", "i": "🔧", "c": "remont-stiralnykh-mashin"}, {"s": "amortizator-stiralnoj-mashiny-bosch-maxx", "t": "Амортизатор стиральной машины Bosch Maxx: замена и диагностика", "i": "🔧", "c": "remont-stiralnykh-mashin"}, {"s": "amortizatory-dlya-stiralnoj-mashiny-kak-otremontirovat", "t": "Как починить амортизаторы стиральной машины своими руками", "i": "🔧", "c": "remont-stiralnykh-mashin"}, {"s": "amortizatory-dlya-stiralnoj-mashiny-ldzhi", "t": "Амортизаторы для стиральной машины LG: замена, выбор и диагностика", "i": "🔧", "c": "remont-stiralnykh-mashin"}, {"s": "amortizatory-na-stiralnuyu-mashinku-bosch", "t": "Амортизаторы на стиральную машину Bosch: выбор и замена", "i": "🔧", "c": "remont-stiralnykh-mashin"}, {"s": "amortizatory-electrolux-dlya-stiralnoj-mashiny", "t": "Амортизаторы Electrolux для стиральной машины: выбор и замена", "i": "🔧", "c": "remont-stiralnykh-mashin"}, {"s": "amortizatory-na-stiralnuyu-mashinu-samsung", "t": "Амортизаторы на стиральную машину Samsung: выбор и замена", "i": "🔧", "c": "remont-stiralnykh-mashin"}, {"s": "amortizatory-dlya-stiralnoj-mashiny-samsung-s821", "t": "Замена амортизаторов для стиральной машины Samsung S821", "i": "🔧", "c": "remont-stiralnykh-mashin"}, {"s": "amortizatory-bosh-na-stiralnuyu-mashinu", "t": "Амортизаторы Бош на стиральную машину: выбор, замена и артикулы", "i": "🔧", "c": "remont-stiralnykh-mashin"}, {"s": "amortizator-dlya-stiralnoj-mashiny-electrolux-ews-1046", "t": "Амортизатор для стиральной машины Electrolux EWS 1046: замена и выбор", "i": "🔧", "c": "remont-stiralnykh-mashin"}, {"s": "amortizatory-dlya-stiralnoj-mashiny-indesit", "t": "Амортизаторы для стиральной машины Indesit: выбор, замена, артикулы", "i": "🔧", "c": "remont-stiralnykh-mashin"}, {"s": "amortizator-barabana-stiralnoj-mashiny-lg", "t": "Амортизатор барабана стиральной машины LG: замена и признаки поломки", "i": "🔧", "c": "remont-stiralnykh-mashin"}, {"s": "amortizator-na-stiralnuyu-mashinu-indezit", "t": "Амортизатор на стиральную машину Indesit: замена и выбор", "i": "🔧", "c": "remont-stiralnykh-mashin"}, {"s": "amortizator-stiralnoj-mashiny-bosch-maxx-5", "t": "Амортизатор стиральной машины Bosch Maxx 5: замена и диагностика", "i": "🔧", "c": "remont-stiralnykh-mashin"}, {"s": "amortizatory-na-stiralnuyu-mashinku-indezit", "t": "Амортизаторы на стиральную машинку Индезит: замена и выбор", "i": "🔧", "c": "remont-stiralnykh-mashin"}, {"s": "amortizatory-dlya-stiralnoj-mashiny-samsung-diamond", "t": "Амортизаторы для стиральной машины Samsung Diamond: выбор и замена", "i": "🔧", "c": "remont-stiralnykh-mashin"}, {"s": "amortizatory-na-stiralnuyu-mashinku", "t": "Амортизаторы на стиральную машинку: замена и выбор", "i": "🔧", "c": "remont-stiralnykh-mashin"}, {"s": "amortizator-dlya-stiralnoj-mashiny-bosch-maxx-4", "t": "Амортизатор стиральной машины Bosch Maxx 4: выбор и замена", "i": "🔧", "c": "remont-stiralnykh-mashin"}, {"s": "amortizator-dlya-stiralnoj-mashiny-candy", "t": "Амортизатор для стиральной машины Candy: выбор, замена, коды", "i": "🔧", "c": "remont-stiralnykh-mashin"}, {"s": "amortizatory-dlya-stiralnoj-mashiny-bosch-logixx-6", "t": "Амортизаторы для стиральной машины Bosch Logixx 6: выбор и замена", "i": "🔧", "c": "remont-stiralnykh-mashin"}, {"s": "amortizatory-dlya-stiralnoj-mashiny-bosch-logixx-8", "t": "Амортизаторы для Bosch Logixx 8: замена и выбор", "i": "🔧", "c": "remont-stiralnykh-mashin"}, {"s": "amortizatory-v-stiralnoj-mashine", "t": "Амортизаторы в стиральной машине: устройство, замена, диагностика", "i": "🔧", "c": "remont-stiralnykh-mashin"}, {"s": "amortizatory-dlya-stiralnoj-mashiny-samsung-wf6450s7w", "t": "Амортизаторы для стиральной машины Samsung WF6450S7W: замена и выбор", "i": "🔧", "c": "remont-stiralnykh-mashin"}, {"s": "amortizatory-dlya-stiralnoj-mashiny-kandi", "t": "Амортизаторы для стиральной машины Канди: как выбрать и заменить", "i": "🔧", "c": "remont-stiralnykh-mashin"}, {"s": "amortizator-dlya-stiralnoj-mashiny-bosch-classixx-5", "t": "Амортизатор для стиральной машины Bosch Classixx 5: замена и выбор", "i": "🔧", "c": "remont-stiralnykh-mashin"}, {"s": "amortizatory-dlya-stiralnoj-mashiny-lg-wd-10180-n", "t": "Амортизаторы для LG WD-10180N: выбор, замена, диагностика", "i": "🔧", "c": "remont-stiralnykh-mashin"}, {"s": "amortizatory-dlya-stiralnoj-mashiny-samsung-s803j", "t": "Амортизаторы для стиральной машины Samsung S803J: замена и выбор", "i": "🔧", "c": "remont-stiralnykh-mashin"}, {"s": "amortizatory-dlya-stiralnoj-mashiny-lg-direct-drive-6-kg", "t": "Амортизаторы для стиральной машины LG Direct Drive 6 кг: выбор и замена", "i": "🔧", "c": "remont-stiralnykh-mashin"}, {"s": "amortizatory-dlya-stiralnoj-mashiny-samsung-fuzzy-s821", "t": "Амортизаторы для стиральной машины Samsung Fuzzy S821: замена и выбор", "i": "🔧", "c": "remont-stiralnykh-mashin"}, {"s": "amortizatory-dlya-stiralnoj-mashinki-samsung", "t": "Амортизаторы для стиральной машины Самсунг: выбор, замена и диагностика", "i": "🔧", "c": "remont-stiralnykh-mashin"}, {"s": "amortizatory-v-stiralnoj-mashine-samsung", "t": "Амортизаторы в стиральной машине Samsung: замена и диагностика", "i": "🔧", "c": "remont-stiralnykh-mashin"}, {"s": "amortizator-dlya-stiralnoj-mashinki-lg", "t": "Амортизатор для стиральной машинки LG: выбор и замена", "i": "🔧", "c": "remont-stiralnykh-mashin"}, {"s": "amortizatory-dlya-stiralnoj-mashiny-elektrolyuks-ewf-1086", "t": "Амортизаторы для стиральной машины Electrolux EWF 1086: замена и выбор", "i": "🔧", "c": "remont-stiralnykh-mashin"}, {"s": "amortizatory-dlya-stiralnoj-mashiny-lg", "t": "Амортизаторы для стиральной машины LG: как выбрать и заменить", "i": "🔧", "c": "remont-stiralnykh-mashin"}]