[{"s": "kak-dostat-baraban-iz-stiralnoj-mashiny-lg", "t": "Как достать барабан из стиральной машины LG: пошаговая инструкция", "i": "🔧", "c": "remont-stiralnykh-mashin"}, {"s": "kak-dostat-shlang-iz-stiralnoj-mashiny", "t": "Как достать шланг из стиральной машины: пошаговая инструкция", "i": "🔧", "c": "remont-stiralnykh-mashin"}, {"s": "kak-demontirovat-stiralnuyu-mashinu", "t": "Как демонтировать стиральную машину: пошаговая инструкция", "i": "🔧", "c": "remont-stiralnykh-mashin"}, {"s": "kak-dostat-emkost-dlya-poroshka-iz-stiralnoj-mashiny-indezit", "t": "Как достать емкость для порошка из стиральной машины Indesit", "i": "🔧", "c": "remont-stiralnykh-mashin"}, {"s": "kak-dostat-filtr-iz-stiralnoj-mashiny-samsung", "t": "Как достать и почистить фильтр стиральной машины Самсунг", "i": "✨", "c": "chistka-i-obsluzhivanie"}, {"s": "kak-dostat-podshipnik-iz-stiralnoj-mashiny-lg", "t": "Как достать подшипник из стиральной машины LG: пошаговая инструкция", "i": "🔧", "c": "remont-stiralnykh-mashin"}, {"s": "kak-dolzhen-rabotat-amortizator-na-stiralnoj-mashine", "t": "Как должен работать амортизатор стиральной машины: диагностика", "i": "🔧", "c": "remont-stiralnykh-mashin"}, {"s": "kak-dostat-lotok-iz-stiralnoj-mashiny", "t": "Как достать лоток из стиральной машины: полная инструкция", "i": "✨", "c": "chistka-i-obsluzhivanie"}, {"s": "kak-dostat-ten-v-stiralnoj-mashine-atlant", "t": "Как достать ТЭН в стиральной машине Атлант: пошаговая инструкция", "i": "🔧", "c": "remont-stiralnykh-mashin"}, {"s": "kak-dostat-iz-stiralnoj-mashinki-otsek-dlya-poroshka", "t": "Как достать отсек для порошка из стиральной машины: инструкция", "i": "✨", "c": "chistka-i-obsluzhivanie"}, {"s": "kak-dostat-v-stiralnoj-mashine-otsek-dlya-poroshka-indezit", "t": "Как достать отсек для порошка в стиральной машине Indesit: инструкция", "i": "🔧", "c": "remont-stiralnykh-mashin"}, {"s": "kak-dostat-filtr-iz-stiralnoj-mashiny-whirlpool", "t": "Как достать фильтр из стиральной машины Whirlpool: инструкция", "i": "✨", "c": "chistka-i-obsluzhivanie"}, {"s": "kak-dostat-nagrevatel-iz-stiralnoj-mashiny", "t": "Как достать нагреватель из стиральной машины: пошаговая инструкция", "i": "🔧", "c": "remont-stiralnykh-mashin"}, {"s": "kak-dolzhna-stirat-mashinka", "t": "Как должна стирать машинка: эталон, признаки и сбои", "i": "✨", "c": "chistka-i-obsluzhivanie"}, {"s": "kak-dostat-s-mashinki-stiralnoj-yashchik-dlya-poroshka", "t": "Как достать ящик для порошка из стиральной машины: пошагово", "i": "✨", "c": "chistka-i-obsluzhivanie"}, {"s": "kak-dolzhen-raspolagatsya-slivnoj-shlang-na-stiralnoj-mashine-indezit", "t": "Правильное расположение сливного шланга стиральной машины Indesit", "i": "🔧", "c": "remont-stiralnykh-mashin"}, {"s": "kak-delayut-kapsuly-dlya-stirki", "t": "Как делают капсулы для стирки: технология производства и состав", "i": "🧴", "c": "bytovaya-khimiya"}, {"s": "kak-dolzhna-rabotat-stiralnaya-mashina-pri-otzhime", "t": "Как должна работать стиральная машина при отжиме: нормы и неисправности", "i": "🔧", "c": "remont-stiralnykh-mashin"}, {"s": "kak-dostat-filtr-iz-stiralnoj-mashiny-kandi", "t": "Как достать фильтр из стиральной машины Candy: пошаговая инструкция", "i": "🔧", "c": "remont-stiralnykh-mashin"}, {"s": "kak-dostat-lotok-dlya-poroshka-iz-stiralnoj-mashiny-lg", "t": "Как достать лоток для порошка из стиральной машины LG: пошаговая инструкция", "i": "✨", "c": "chistka-i-obsluzhivanie"}, {"s": "kak-dostat-lotok-iz-stiralnoj-mashiny-samsung", "t": "Как достать лоток из стиральной машины Samsung: полная инструкция", "i": "🔧", "c": "remont-stiralnykh-mashin"}, {"s": "kak-dobratsya-do-filtra-v-stiralnoj-mashine-indezit", "t": "Как добраться до фильтра в стиральной машине Indesit: инструкция", "i": "🔧", "c": "remont-stiralnykh-mashin"}, {"s": "kak-dostat-iz-stiralnoj-mashiny-otsek-dlya-poroshka-atlant", "t": "Как достать лоток для порошка из стиральной машины Атлант", "i": "✨", "c": "chistka-i-obsluzhivanie"}, {"s": "kak-dostat-so-stiralnoj-mashiny-otsek-dlya-poroshka", "t": "Как достать отсек для порошка стиральной машины: инструкция", "i": "✨", "c": "chistka-i-obsluzhivanie"}, {"s": "kak-doma-postirat-palto-iz-kashemira", "t": "Как постирать кашемировое пальто дома: полная инструкция", "i": "👕", "c": "ukhod-za-tkanyami"}, {"s": "kak-doma-postirat-pukhovuyu-podushku", "t": "Как постирать пуховую подушку дома: полная инструкция", "i": "👕", "c": "ukhod-za-tkanyami"}, {"s": "kak-dostat-slivnoj-filtr-iz-stiralnoj-mashiny", "t": "Как достать сливной фильтр из стиральной машины: пошаговая инструкция", "i": "🔧", "c": "remont-stiralnykh-mashin"}, {"s": "kak-doma-postirat-kover", "t": "Как постирать ковер дома: пошаговая инструкция и советы", "i": "👕", "c": "ukhod-za-tkanyami"}, {"s": "kak-dostat-iz-stiralnoj-mashiny-otsek-dlya-poroshka-lg", "t": "Как достать отсек для порошка LG: пошаговая инструкция", "i": "✨", "c": "chistka-i-obsluzhivanie"}, {"s": "kak-dobavit-bele-vo-vremya-stirki-v-lg", "t": "Как добавить белье в LG: полная инструкция", "i": "🔧", "c": "remont-stiralnykh-mashin"}, {"s": "kak-dolzhen-idti-slivnoj-shlang-stiralnoj-mashiny-pravilno", "t": "Как правильно подключить сливной шланг стиральной машины", "i": "🔧", "c": "remont-stiralnykh-mashin"}, {"s": "kak-dostat-otdel-dlya-poroshka-v-stiralnoj-mashine-samsung", "t": "Как достать лоток для порошка в стиральной машине Самсунг", "i": "✨", "c": "chistka-i-obsluzhivanie"}, {"s": "kak-dostat-filtr-iz-stiralnoj-mashiny-indezit", "t": "Как достать фильтр из стиральной машины Indesit: пошаговая инструкция", "i": "🔧", "c": "remont-stiralnykh-mashin"}, {"s": "kak-dostat-otsek-dlya-poroshka-iz-stiralnoj", "t": "Как достать отсек для порошка из стиральной машины: инструкция", "i": "✨", "c": "chistka-i-obsluzhivanie"}, {"s": "kak-dostat-filtr-iz-stiralnoj-mashiny-lg", "t": "Как достать фильтр из стиральной машины LG: инструкция", "i": "✨", "c": "chistka-i-obsluzhivanie"}, {"s": "kak-dobratsya-do-nasosa-v-stiralnoj-mashine-samsung", "t": "Как добраться до насоса в стиральной машине Самсунг: полная инструкция", "i": "🔧", "c": "remont-stiralnykh-mashin"}, {"s": "kak-dostat-baraban-iz-stiralnoj-mashiny-atlant", "t": "Как достать барабан из стиральной машины Атлант: пошаговая инструкция", "i": "🔧", "c": "remont-stiralnykh-mashin"}, {"s": "kak-dostat-poroshkopriemnik-iz-stiralnoj-mashiny-indezit", "t": "Как достать порошкоприемник из стиральной машины Indesit", "i": "🔧", "c": "remont-stiralnykh-mashin"}, {"s": "kak-doma-postirat-palto", "t": "Как постирать пальто дома: полное руководство по уходу", "i": "🧥", "c": "stirka-verkhnej-odezhdy"}, {"s": "kak-dostat-lotok-dlya-poroshka-iz-stiralnoj-mashiny-samsung", "t": "Как достать лоток для порошка из стиральной машины Samsung", "i": "✨", "c": "chistka-i-obsluzhivanie"}, {"s": "kak-dostat-lotok-dlya-poroshka-iz-stiralnoj", "t": "Как достать лоток для порошка из стиральной машины: инструкция", "i": "✨", "c": "chistka-i-obsluzhivanie"}, {"s": "kak-dostat-ten-v-stiralnoj-mashine-lg", "t": "Как достать ТЭН в стиральной машине LG: пошаговая инструкция", "i": "🔧", "c": "remont-stiralnykh-mashin"}, {"s": "kak-dobavit-konditsioner-v-stiralnuyu-mashinu-avtomat", "t": "Как добавить кондиционер в стиральную машину: секреты дозатора", "i": "🧴", "c": "bytovaya-khimiya"}, {"s": "kak-domashnimi-sredstvami-pochistit-stiralnuyu-mashinu", "t": "Чистка стиральной машины: лучшие домашние средства", "i": "✨", "c": "chistka-i-obsluzhivanie"}, {"s": "kak-dobratsya-do-barabana-stiralnoj-mashiny-indezit", "t": "Как добраться до барабана стиральной машины Indesit", "i": "🔧", "c": "remont-stiralnykh-mashin"}, {"s": "kak-dobratsya-do-podshipnika-v-stiralnoj-mashine-lg", "t": "Как добраться до подшипника в стиральной машине LG: полная инструкция", "i": "🔧", "c": "remont-stiralnykh-mashin"}, {"s": "kak-doma-postirat-pukhovik", "t": "Как постирать пуховик дома: полная инструкция", "i": "🧥", "c": "stirka-verkhnej-odezhdy"}, {"s": "kak-dostat-filtr-v-stiralnoj-mashine", "t": "Как достать и почистить фильтр в стиральной машине: инструкция", "i": "✨", "c": "chistka-i-obsluzhivanie"}, {"s": "kak-dostat-lotok-dlya-poroshka-iz-stiralnoj-mashiny-indezit", "t": "Как достать лоток порошка из стиральной машины Indesit: инструкция", "i": "✨", "c": "chistka-i-obsluzhivanie"}, {"s": "kak-delat-ochistku-barabana-stiralnoj-mashiny-lg", "t": "Очистка барабана стиральной машины LG: пошаговая инструкция", "i": "✨", "c": "chistka-i-obsluzhivanie"}, {"s": "kak-dostat-emkost-dlya-poroshka-iz-stiralnoj-mashiny-lg", "t": "Как достать лоток для порошка из стиральной машины LG: инструкция", "i": "✨", "c": "chistka-i-obsluzhivanie"}, {"s": "kak-dostat-kontejner-dlya-poroshka-iz-stiralnoj-mashiny-samsung", "t": "Как достать контейнер для порошка из стиральной машины Samsung", "i": "✨", "c": "chistka-i-obsluzhivanie"}, {"s": "kak-dostat-korobku-dlya-poroshka-iz-stiralnoj-mashiny-indezit", "t": "Как достать лоток для порошка из стиральной машины Indesit: полная инструкция", "i": "🔧", "c": "remont-stiralnykh-mashin"}, {"s": "kak-dostat-otsek-dlya-poroshka-iz-stiralnoj-mashiny-bosh", "t": "Как достать лоток из стиральной машины Bosch: пошаговая инструкция", "i": "🔧", "c": "remont-stiralnykh-mashin"}, {"s": "kak-dostat-ten-iz-stiralnoj-mashiny-indezit", "t": "Как достать ТЭН из стиральной машины Indesit: пошаговая инструкция", "i": "🔧", "c": "remont-stiralnykh-mashin"}, {"s": "kak-dostat-bele-iz-stiralnoj-mashiny-esli-ona-zavisla", "t": "Как достать белье из зависшей стиральной машины: инструкция", "i": "📁", "c": null}, {"s": "kak-dostat-filtr-iz-stiralnoj-mashiny-bosh", "t": "Как достать фильтр из стиральной машины Bosch: инструкция", "i": "✨", "c": "chistka-i-obsluzhivanie"}, {"s": "kak-dostat-iz-stiralnoj-mashiny-otsek-dlya-poroshka", "t": "Как достать отсек для порошка из стиральной машины: пошаговая инструкция", "i": "✨", "c": "chistka-i-obsluzhivanie"}, {"s": "kak-dostat-ten-iz-stiralnoj-mashiny", "t": "Как достать ТЭН из стиральной машины: пошаговая инструкция", "i": "🔧", "c": "remont-stiralnykh-mashin"}, {"s": "kak-dostat-dozator-iz-stiralnoj-mashiny-indezit", "t": "Как достать дозатор из стиральной машины Индезит: пошаговая инструкция", "i": "🔧", "c": "remont-stiralnykh-mashin"}, {"s": "kak-dostat-raspredelitel-moyushchikh-sredstv-v-stiralnoj-mashine-indezit", "t": "Как достать распределитель моющих средств в стиральной машине Индезит", "i": "🔧", "c": "remont-stiralnykh-mashin"}, {"s": "kak-dostat-ten-v-stiralnoj-mashine", "t": "Как достать ТЭН в стиральной машине: пошаговая инструкция", "i": "🔧", "c": "remont-stiralnykh-mashin"}, {"s": "kak-dobratsya-do-barabana-stiralnoj-mashiny", "t": "Как добраться до барабана стиральной машины: пошаговая инструкция", "i": "📁", "c": null}, {"s": "kak-dostat-lotok-dlya-poroshka-iz-stiralnoj-mashiny", "t": "Как достать лоток для порошка из стиральной машины: пошаговая инструкция", "i": "✨", "c": "chistka-i-obsluzhivanie"}, {"s": "kak-dostat-lotok-iz-stiralnoj-mashiny-indezit", "t": "Как достать лоток из стиральной машины Indesit: пошаговая инструкция", "i": "🔧", "c": "remont-stiralnykh-mashin"}, {"s": "kak-delat-ochistku-barabana-stiralnoj-mashiny-samsung", "t": "Очистка барабана стиральной машины Samsung: пошаговая инструкция", "i": "✨", "c": "chistka-i-obsluzhivanie"}, {"s": "kak-dozirovat-gel-dlya-stirki-tajd", "t": "Как дозировать гель для стирки Тайд: точные пропорции", "i": "🧴", "c": "bytovaya-khimiya"}, {"s": "kak-delat-pervyj-zapusk-stiralnoj-mashiny", "t": "Первый запуск стиральной машины: пошаговая инструкция", "i": "🏠", "c": "obzory-tekhniki"}, {"s": "kak-dostat-kontejner-dlya-poroshka-iz-stiralnoj-mashiny-indezit", "t": "Как достать лоток порошка из стиральной машины Indesit", "i": "✨", "c": "chistka-i-obsluzhivanie"}, {"s": "kak-dostat-podshipnik-iz-stiralnoj-mashiny", "t": "Как достать подшипник из стиральной машины: полная инструкция", "i": "🔧", "c": "remont-stiralnykh-mashin"}, {"s": "kak-dobavlyat-zhidkij-vanish-v-stiralnuyu-mashinu", "t": "Как добавлять жидкий Vanish в стиральную машину: инструкция", "i": "🧴", "c": "bytovaya-khimiya"}, {"s": "kak-dostat-baraban-iz-stiralnoj-mashiny", "t": "Как достать барабан из стиральной машины: пошаговая инструкция", "i": "🔧", "c": "remont-stiralnykh-mashin"}, {"s": "kak-dostat-filtr-iz-stiralnoj-mashiny-atlant", "t": "Как достать фильтр из стиральной машины Атлант: инструкция", "i": "✨", "c": "chistka-i-obsluzhivanie"}, {"s": "kak-dostat-ten-v-stiralnoj-mashine-indezit", "t": "Как достать ТЭН в стиральной машине Indesit: пошаговая инструкция", "i": "🔧", "c": "remont-stiralnykh-mashin"}]