[{"s": "lyuk-stiralnoj-mashiny-bosch-maxx", "t": "Люк стиральной машины Bosch Maxx: ремонт, регулировка и замена", "i": "🔧", "c": "remont-stiralnykh-mashin"}, {"s": "lyuk-ot-stiralnoj-mashiny-candy", "t": "Люк от стиральной машины Candy: замена, ремонт, цена", "i": "🔧", "c": "remont-stiralnykh-mashin"}, {"s": "lyuk-stiralnoj-mashiny-indesit", "t": "Люк стиральной машины Indesit: замена, ремонт и регулировка", "i": "🔧", "c": "remont-stiralnykh-mashin"}, {"s": "lyuk-stiralnoj-mashiny-bosch-logixx", "t": "Люк стиральной машины Bosch Logixx: устройство, ремонт и уплотнитель", "i": "🔧", "c": "remont-stiralnykh-mashin"}, {"s": "lyuk-na-stiralnuyu-mashinu-indezit", "t": "Люк на стиральную машину Индезит: замена, петли и уплотнитель", "i": "🔧", "c": "remont-stiralnykh-mashin"}, {"s": "lyuk-stiralnoj-mashiny-bosh", "t": "Замена люка стиральной машины Бош: пошаговая инструкция", "i": "🔧", "c": "remont-stiralnykh-mashin"}, {"s": "lyuk-stiralnaya-mashina-kandi", "t": "Люк стиральной машины Candy: ремонт, замена, коды ошибок", "i": "🔧", "c": "remont-stiralnykh-mashin"}, {"s": "lyuk-stiralnoj-mashiny-electrolux", "t": "Люк стиральной машины Electrolux: устройство, ремонт и замена", "i": "🔧", "c": "remont-stiralnykh-mashin"}, {"s": "lyuk-stiralnoj-mashiny-bosch", "t": "Люк стиральной машины Bosch: устройство, ремонт и регулировка", "i": "🔧", "c": "remont-stiralnykh-mashin"}, {"s": "lyuk-stiralnoj-mashiny-samsung", "t": "Люк стиральной машины Самсунг: устройство, ремонт и замена", "i": "🔧", "c": "remont-stiralnykh-mashin"}, {"s": "lyuk-stiralnoj-mashiny-bosch-logixx-8", "t": "Люк стиральной машины Bosch Logixx 8: ремонт, разборка и уплотнитель", "i": "🔧", "c": "remont-stiralnykh-mashin"}, {"s": "lyuk-stiralnoj-mashiny-bosch-maxx-5", "t": "Люк стиральной машины Bosch Maxx 5: ремонт и замена уплотнителя", "i": "🔧", "c": "remont-stiralnykh-mashin"}, {"s": "lyuk-stiralnoj-mashiny-bosch-serie-6", "t": "Люк стиральной машины Bosch Serie 6: замена и ремонт", "i": "🔧", "c": "remont-stiralnykh-mashin"}, {"s": "lyuk-stiralnoj-mashiny-lg", "t": "Люк стиральной машины LG: ремонт, разборка и замена стекла", "i": "🔧", "c": "remont-stiralnykh-mashin"}, {"s": "lyuk-stiralnoj-mashiny-ne-otkryvaetsya", "t": "Люк стиральной машины не открывается: причины и ремонт", "i": "🔧", "c": "remont-stiralnykh-mashin"}]