[{"s": "meine-liebe-poroshok-dlya-stirki", "t": "Порошок Meine Liebe для стирки: обзор, состав и отзывы", "i": "🧴", "c": "bytovaya-khimiya"}, {"s": "meine-liebe-zhidkoe-sredstvo-dlya-stirki-detskogo-belya-kontsentrat-3-l", "t": "Meine Liebe 3л: Концентрат для стирки детского белья", "i": "🧴", "c": "bytovaya-khimiya"}, {"s": "metro-gel-dlya-stirki", "t": "Метро Гель для стирки: состав, эффективность и отзывы экспертов", "i": "🧴", "c": "bytovaya-khimiya"}, {"s": "meine-liebe-dlya-stirki", "t": "Жидкий порошок Meine Liebe: полное руководство и применение", "i": "🧴", "c": "bytovaya-khimiya"}, {"s": "meine-liebe-sredstvo-dlya-stirki", "t": "Meine Liebe средство для стирки: обзор, отзывы и состав", "i": "🧴", "c": "bytovaya-khimiya"}, {"s": "meshki-dlya-stirki-belya-fiks-prajs", "t": "Мешки для стирки белья Фикс Прайс: лучшие модели и отзывы", "i": "🎱", "c": "aksessuary-dlya-stirki"}, {"s": "meshochek-dlya-stirki-byustgaltera", "t": "Мешочек для стирки бюстгальтера: выбор, виды и секреты ухода", "i": "🎱", "c": "aksessuary-dlya-stirki"}, {"s": "meshok-setka-dlya-stirki-belya-v-stiralnoj-mashine", "t": "Мешок сетка для стирки белья: как выбрать и использовать", "i": "🎱", "c": "aksessuary-dlya-stirki"}, {"s": "metro-kapsuly-dlya-stirki", "t": "Капсулы для стирки: плюсы, минусы и рейтинг 2026", "i": "🧴", "c": "bytovaya-khimiya"}, {"s": "meshochki-dlya-stirki-belya", "t": "Мешочки для стирки: виды, размеры и как правильно выбрать", "i": "🎱", "c": "aksessuary-dlya-stirki"}, {"s": "meshok-dlya-stirki-ozon", "t": "Мешок для стирки Ozon: как выбрать и использовать правильно", "i": "🎱", "c": "aksessuary-dlya-stirki"}, {"s": "meshok-setka-dlya-stirki-belya", "t": "Мешок сетка для стирки: как выбрать и использовать правильно", "i": "🎱", "c": "aksessuary-dlya-stirki"}, {"s": "meshki-dlya-gryaznogo-belya", "t": "Мешки для грязного белья: выбор, материалы и советы по уходу", "i": "🎱", "c": "aksessuary-dlya-stirki"}, {"s": "meshki-dlya-transportirovki-belya-v-prachechnuyu", "t": "Мешки для транспортировки белья: выбор и особенности", "i": "📁", "c": null}, {"s": "meshok-dlya-delikatnoj-stirki", "t": "Мешок для деликатной стирки: выбор и применение", "i": "🎱", "c": "aksessuary-dlya-stirki"}, {"s": "mernaya-lozhka-dlya-poroshka", "t": "Мерная ложка для порошка: виды, объём, где купить", "i": "🎱", "c": "aksessuary-dlya-stirki"}, {"s": "meshochek-dlya-stirki-byustgaltera-faberlik", "t": "Мешочек для стирки бюстгальтера Фаберлик: как выбрать и использовать", "i": "🎱", "c": "aksessuary-dlya-stirki"}, {"s": "meule-stiralnyj-poroshok-otzyvy", "t": "Meule стиральный порошок: отзывы, состав и реальная эффективность", "i": "🧴", "c": "bytovaya-khimiya"}, {"s": "meine-liebe-gel-dlya-stirki-detskogo-belya-otzyvy", "t": "Meine Liebe гель для стирки: отзывы, состав и безопасность", "i": "🧴", "c": "bytovaya-khimiya"}, {"s": "meshok-dlya-nizhnego-belya", "t": "Мешок для нижнего белья: как правильно стирать деликатные вещи", "i": "🎱", "c": "aksessuary-dlya-stirki"}, {"s": "meine-liebe-poroshok-dlya-novorozhdennykh", "t": "Meine Liebe порошок для новорожденных: состав и отзывы", "i": "🧴", "c": "bytovaya-khimiya"}, {"s": "menyaem-amortizatory-na-stiralnoj-mashine-indezit", "t": "Замена амортизаторов на стиральной машине Indesit: пошаговая инструкция", "i": "📁", "c": null}, {"s": "meshki-dlya-stirki-krossovok", "t": "Мешки для стирки кроссовок: как выбрать и стирать обувь", "i": "📁", "c": null}, {"s": "meshochek-dlya-stirki-belya-v-mashinke", "t": "Мешочек для стирки белья: как выбрать и использовать", "i": "🎱", "c": "aksessuary-dlya-stirki"}, {"s": "meine-liebe-stiralnyj-poroshok-dlya-detskogo-belya", "t": "Стиральный порошок Meine Liebe для детей: обзор и отзывы", "i": "🧴", "c": "bytovaya-khimiya"}, {"s": "menyaem-ten-na-stiralnoj-mashine-samsung", "t": "Как заменить ТЭН в стиральной машине Samsung: пошаговая инструкция", "i": "🔧", "c": "remont-stiralnykh-mashin"}, {"s": "meine-liebe-poroshok-proizvoditel", "t": "Meine Liebe порошок: производитель, отзывы и состав", "i": "🧴", "c": "bytovaya-khimiya"}, {"s": "meshok-dlya-stirki-byustgalterov-v-stiralnoj-mashine", "t": "Мешок для стирки бюстгальтеров: как выбрать и использовать", "i": "🎱", "c": "aksessuary-dlya-stirki"}, {"s": "meshok-dlya-stirki-dlya-chego", "t": "Мешок для стирки: для чего нужен, как выбрать и пользоваться", "i": "🎱", "c": "aksessuary-dlya-stirki"}, {"s": "meshki-dlya-belya-v-prachechnuyu", "t": "Мешки для белья в прачечную: виды, размеры и правила стирки", "i": "🎱", "c": "aksessuary-dlya-stirki"}, {"s": "meshok-dlya-belya-v-prachechnuyu-s-zavyazkami", "t": "Мешок для белья в прачечную с завязками: как выбрать и использовать", "i": "🎱", "c": "aksessuary-dlya-stirki"}, {"s": "meshok-dlya-stirki-belya-zachem-nuzhen", "t": "Мешок для стирки белья: зачем нужен и как выбрать правильно", "i": "🎱", "c": "aksessuary-dlya-stirki"}, {"s": "meine-liebe-dlya-detskogo-belya", "t": "Meine Liebe для детского белья: обзор и отзывы", "i": "🧴", "c": "bytovaya-khimiya"}, {"s": "meine-liebe-gel-dlya-stirki-otzyvy", "t": "Meine Liebe гель для стирки: отзывы, обзор и состав", "i": "🧴", "c": "bytovaya-khimiya"}, {"s": "meine-liebe-poroshok-universalnyj-otzyvy", "t": "Порошок Meine Liebe: отзывы, состав и эффективность", "i": "🧴", "c": "bytovaya-khimiya"}, {"s": "membrannyj-poroshok-dlya-stirki", "t": "Мембранный порошок для стирки: как выбрать и использовать", "i": "👕", "c": "ukhod-za-tkanyami"}, {"s": "meshki-dlya-belya-fiks-prajs", "t": "Мешки для белья Fix Price: виды, размеры и как правильно использовать", "i": "🎱", "c": "aksessuary-dlya-stirki"}, {"s": "meshok-dlya-stirki-lifchikov", "t": "Мешок для стирки лифчиков: выбор и правила использования", "i": "🎱", "c": "aksessuary-dlya-stirki"}, {"s": "meshok-dlya-stirki-krossovok-v-stiralnoj-mashine", "t": "Мешок для стирки кроссовок: как выбрать и использовать", "i": "🎱", "c": "aksessuary-dlya-stirki"}, {"s": "meshok-dlya-stirki-veshchej", "t": "Мешок для стирки вещей: виды, размеры и как выбрать сетку", "i": "🎱", "c": "aksessuary-dlya-stirki"}, {"s": "meine-liebe-stiralnyj-poroshok-otzyvy", "t": "Meine Liebe стиральный порошок: отзывы, разбор состава и эффективность", "i": "🧴", "c": "bytovaya-khimiya"}, {"s": "mepsi-stiralnyj-poroshok-proizvoditel", "t": "Mepsi стиральный порошок: производитель, состав и отзывы", "i": "🧴", "c": "bytovaya-khimiya"}, {"s": "meshok-dlya-stirki-byustgalterov", "t": "Мешок для стирки бюстгальтеров: защита и уход за бельем", "i": "🎱", "c": "aksessuary-dlya-stirki"}, {"s": "meshok-dlya-stirki-kurtki-v-stiralnoj-mashine", "t": "Мешок для стирки куртки: как выбрать и правильно использовать", "i": "📁", "c": null}, {"s": "meshok-dlya-stirki-v-stiralnoj-mashine", "t": "Мешок для стирки в стиральной машине: как выбрать и использовать", "i": "🎱", "c": "aksessuary-dlya-stirki"}, {"s": "menyaem-podshipnik-na-stiralnoj-mashine", "t": "Замена подшипника стиральной машины: пошаговая инструкция", "i": "🔧", "c": "remont-stiralnykh-mashin"}, {"s": "meshok-dlya-obuvi-dlya-stirki-v-stiralnoj-mashine", "t": "Мешок для обуви для стирки: как выбрать и правильно использовать", "i": "🎱", "c": "aksessuary-dlya-stirki"}, {"s": "meshochek-dlya-stirki-nizhnego-belya", "t": "Мешочек для стирки нижнего белья: виды, правила и ошибки", "i": "📁", "c": null}, {"s": "meshok-dlya-stirki-byustgalterov-v-stiralnoj-mashine-otzyvy", "t": "Мешок для стирки бюстгальтеров в стиральной машине отзывы: рейтинг лучших 2026", "i": "🎱", "c": "aksessuary-dlya-stirki"}, {"s": "meshok-dlya-stirki-obuvi-v-stiralnoj-mashine-fiks-prajs", "t": "Мешок для стирки обуви в стиральной машине: выбор и отзывы о Fix Price", "i": "🎱", "c": "aksessuary-dlya-stirki"}, {"s": "membrannaya-kurtka-kak-stirat", "t": "Как стирать мембранную куртку: правила и советы экспертов", "i": "🧥", "c": "stirka-verkhnej-odezhdy"}, {"s": "membrannaya-tkan-kak-stirat", "t": "Мембранная ткань как стирать: полная инструкция по уходу", "i": "👕", "c": "ukhod-za-tkanyami"}, {"s": "meshok-dlya-stirki-nizhnego-belya-v-stiralnoj-mashine", "t": "Мешок для стирки нижнего белья: выбор, виды и инструкция", "i": "🎱", "c": "aksessuary-dlya-stirki"}, {"s": "meshok-dlya-stirki-noskov-v-stiralnoj-mashine", "t": "Мешок для стирки носков: как выбрать и использовать правильно", "i": "🎱", "c": "aksessuary-dlya-stirki"}, {"s": "mernaya-emkost-dlya-stiralnogo-poroshka-v-baraban", "t": "Мерная емкость для стирального порошка в барабан: виды, дозировки, ошибки", "i": "🎱", "c": "aksessuary-dlya-stirki"}, {"s": "meshok-setka-dlya-stirki", "t": "Мешок сетка для стирки: виды, выбор и правила применения", "i": "🎱", "c": "aksessuary-dlya-stirki"}, {"s": "meshok-dlya-berezhnoj-stirki", "t": "Мешок для бережной стирки: как выбрать и использовать правильно", "i": "🎱", "c": "aksessuary-dlya-stirki"}, {"s": "meshok-dlya-stiralnoj-mashiny", "t": "Мешок для стиральной машины: зачем нужен и как выбрать", "i": "🎱", "c": "aksessuary-dlya-stirki"}, {"s": "meshok-dlya-stirki-belya-v-stiralnoj-mashine-fiks-prajs", "t": "Мешок для стирки белья в стиральной машине Фикс Прайс: выбор и отзывы", "i": "🎱", "c": "aksessuary-dlya-stirki"}, {"s": "meshok-dlya-stirki-noskov", "t": "Мешок для стирки носков: как выбрать сетку и не потерять пары", "i": "🎱", "c": "aksessuary-dlya-stirki"}, {"s": "meshok-dlya-stirki-pukhovika-v-stiralnoj", "t": "Мешок для стирки пуховика в стиральной: как выбрать и использовать", "i": "🧥", "c": "stirka-verkhnej-odezhdy"}, {"s": "membrannaya-odezhda-chem-stirat", "t": "Чем стирать мембранную одежду: гид по средствам и уходу", "i": "🧥", "c": "stirka-verkhnej-odezhdy"}, {"s": "meshochki-dlya-khraneniya-nizhnego-belya", "t": "Мешочки для стирки нижнего белья: как выбрать и использовать", "i": "🎱", "c": "aksessuary-dlya-stirki"}, {"s": "meshochki-dlya-stirki-obuvi", "t": "Мешочки для стирки обуви: как выбрать и постирать кроссовки", "i": "🎱", "c": "aksessuary-dlya-stirki"}, {"s": "meshki-dlya-stirki-belya", "t": "Мешки для стирки белья: как выбрать и использовать сетку", "i": "🎱", "c": "aksessuary-dlya-stirki"}, {"s": "meshki-dlya-stirki-ikea", "t": "Мешки для стирки Икеа: обзор, отзывы и как выбрать", "i": "🎱", "c": "aksessuary-dlya-stirki"}, {"s": "meine-liebe-detskij-stiralnyj-poroshok", "t": "Meine Liebe детский стиральный порошок: состав, отзывы и инструкция", "i": "🧴", "c": "bytovaya-khimiya"}, {"s": "meine-liebe-gel-dlya-stirki-tsvetnykh-tkanej-kontsentrat-800ml", "t": "Meine Liebe гель для цветных тканей 800 мл: обзор, состав и дозировка", "i": "🧴", "c": "bytovaya-khimiya"}, {"s": "meshok-dlya-obuvi-dlya-stirki", "t": "Мешок для обуви для стирки: выбор, виды и правила использования", "i": "🎱", "c": "aksessuary-dlya-stirki"}, {"s": "meshok-dlya-stirki-nizhnego-belya", "t": "Мешок для стирки нижнего белья: как выбрать и использовать правильно", "i": "🎱", "c": "aksessuary-dlya-stirki"}, {"s": "meshok-dlya-belya-na-opore-ikea", "t": "Мешок для белья на опоре ИКЕА: обзор, размеры и лайфхаки", "i": "🎱", "c": "aksessuary-dlya-stirki"}, {"s": "medlenno-nabiraetsya-voda-v-stiralnoj-mashine", "t": "Медленно набирается вода в стиральной машине: причины и ремонт", "i": "🔧", "c": "remont-stiralnykh-mashin"}, {"s": "meshok-dlya-stirki-belya-v-stiralnoj-mashine", "t": "Мешок для стирки белья: как выбрать и использовать сетку", "i": "🎱", "c": "aksessuary-dlya-stirki"}, {"s": "meshok-dlya-stirki-magnit-kosmetik", "t": "Мешок для стирки магнит косметик: защита вещей и машины", "i": "📁", "c": null}, {"s": "meshok-dlya-stirki-shtor-v-stiralnoj-mashine", "t": "Мешок для стирки штор в стиральной машине: выбор и применение", "i": "🎱", "c": "aksessuary-dlya-stirki"}, {"s": "meshok-dlya-stirki-shtor", "t": "Мешок для стирки штор: выбор, размеры и правила ухода", "i": "🎱", "c": "aksessuary-dlya-stirki"}, {"s": "meshki-dlya-postelnogo-belya", "t": "Мешки для постельного белья: виды, размеры и правила стирки", "i": "🎱", "c": "aksessuary-dlya-stirki"}, {"s": "meine-liebe-poroshok-dlya-novorozhdennykh-otzyvy", "t": "Meine Liebe порошок для новорожденных: отзывы, состав и анализ", "i": "🧴", "c": "bytovaya-khimiya"}, {"s": "mernyj-kolpachok-dlya-stirki", "t": "Мерный колпачок для стирки: как правильно пользоваться", "i": "🎱", "c": "aksessuary-dlya-stirki"}, {"s": "mernyj-stakan-dlya-stiralnogo-poroshka", "t": "Мерный стакан для стирального порошка: виды, дозировка и секреты", "i": "🧴", "c": "bytovaya-khimiya"}, {"s": "meshok-dlya-stirki-belya-v-stiralnoj-mashine-ozon", "t": "Мешок для стирки белья в стиральной машине: как выбрать на Ozon", "i": "📁", "c": null}, {"s": "mernaya-lozhka-dlya-stiralnogo-poroshka", "t": "Мерная ложка для стирального порошка: таблица дозировок и правила", "i": "📁", "c": null}, {"s": "meine-liebe-gel-dlya-stirki-detskogo-belya", "t": "Meine Liebe гель для стирки детского белья: обзор и свойства", "i": "🧴", "c": "bytovaya-khimiya"}, {"s": "mekh-mozhno-stirat-naturalnyj", "t": "Можно ли стирать натуральный мех: инструкции и запреты", "i": "🧥", "c": "stirka-verkhnej-odezhdy"}, {"s": "meshki-dlya-stirki-belya-v-stiralnoj", "t": "Мешки для стирки белья: зачем нужны и как выбрать", "i": "🎱", "c": "aksessuary-dlya-stirki"}, {"s": "meshok-dlya-stirki-pukhovika-v-stiralnoj-mashine", "t": "Мешок для стирки пуховика: как выбрать и использовать правильно", "i": "🎱", "c": "aksessuary-dlya-stirki"}, {"s": "meshochki-dlya-nizhnego-belya", "t": "Мешочки для нижнего белья: как стирать и какой выбрать", "i": "🎱", "c": "aksessuary-dlya-stirki"}, {"s": "meshok-dlya-stirki-krossovok-fiks-prajs", "t": "Мешок для стирки кроссовок: выбор и обзор моделей Фикс Прайс", "i": "🎱", "c": "aksessuary-dlya-stirki"}, {"s": "meine-liebe-konditsioner-dlya-belya", "t": "Кондиционер для белья Meine Liebe: обзор, инструкция и советы", "i": "🧴", "c": "bytovaya-khimiya"}, {"s": "melodiya-stiralnoj-mashiny-lg", "t": "Мелодия стиральной машины LG: коды ошибок и расшифровка", "i": "📁", "c": null}, {"s": "meshochki-dlya-stirki-krossovok-v-stiralnoj-mashine", "t": "Мешок для стирки кроссовок: как стирать обувь в машине", "i": "🎱", "c": "aksessuary-dlya-stirki"}, {"s": "meshok-dlya-stirki-dlya-chego-nuzhen", "t": "Мешок для стирки: для чего нужен, как выбрать и пользоваться", "i": "🎱", "c": "aksessuary-dlya-stirki"}, {"s": "meshok-dlya-stirki-podushek-v-stiralnoj-mashine", "t": "Мешок для стирки подушек: как выбрать и использовать правильно", "i": "🎱", "c": "aksessuary-dlya-stirki"}]