[{"s": "whirlpool-stiralnaya-mashina-awe-2214-1-instruktsiya", "t": "Whirlpool AWE 2214/1: Инструкция, коды ошибок и ремонт", "i": "🔧", "c": "remont-stiralnykh-mashin"}, {"s": "whirlpool-stiralnaya-mashina-verkhnyaya-zagruzka", "t": "Стиральная машина Whirlpool с верхней загрузкой: обзор и выбор", "i": "🏠", "c": "obzory-tekhniki"}, {"s": "whirlpool-stiralnaya-mashina-kak-polzovatsya", "t": "Whirlpool стиральная машина: как пользоваться, режимы и уход", "i": "🏠", "c": "obzory-tekhniki"}, {"s": "whirlpool-stiralnaya-mashina-vertikalnaya", "t": "Стиральная машина Whirlpool вертикальная: Обзор, модели и ремонт", "i": "🏠", "c": "obzory-tekhniki"}, {"s": "whirlpool-kak-vklyuchit-stiralku", "t": "Как включить стиральную машину Whirlpool: пошаговая инструкция", "i": "🔧", "c": "remont-stiralnykh-mashin"}, {"s": "whirlpool-stiralnaya-mashina-kak-vklyuchit", "t": "Whirlpool стиральная машина: как включить и настроить", "i": "🏠", "c": "obzory-tekhniki"}, {"s": "whirlpool-stiralnaya-mashina-s-vertikalnoj-zagruzkoj-instruktsiya-na-russkom-yazyke", "t": "Whirlpool вертикальная стиральная машина: инструкция и коды ошибок", "i": "👕", "c": "ukhod-za-tkanyami"}, {"s": "whirlpool-stiralnaya-mashina-s-vertikalnoj-zagruzkoj-remont", "t": "Ремонт стиральных машин Whirlpool с вертикальной загрузкой: неисправности", "i": "🔧", "c": "remont-stiralnykh-mashin"}, {"s": "whirlpool-kuda-zasypat-poroshok", "t": "Whirlpool куда засыпать порошок: схема лотка и дозировки", "i": "📁", "c": null}, {"s": "whirlpool-stiralnaya-mashina-otzyvy-pokupatelej-i-spetsialistov", "t": "Whirlpool стиральная машина: отзывы, поломки и советы", "i": "🏠", "c": "obzory-tekhniki"}, {"s": "whirlpool-stiralnaya-mashina-vertikalnaya-kak-polzovatsya", "t": "Стиральная машина Whirlpool вертикальная: инструкция и режимы", "i": "🏠", "c": "obzory-tekhniki"}, {"s": "whirlpool-stiralnaya-mashina-awe-2221-instruktsiya-po-primeneniyu", "t": "Whirlpool AWE 2221: инструкция, характеристики и ремонт", "i": "🏠", "c": "obzory-tekhniki"}, {"s": "whirlpool-stiralnaya-mashina-oshibka-f01", "t": "Ошибка F01 Whirlpool: причины сбоя и методы ремонта", "i": "🔧", "c": "remont-stiralnykh-mashin"}, {"s": "whirlpool-stiralnaya-mashina-6-sense", "t": "Стиральная машина Whirlpool 6th Sense: обзор, режимы и коды ошибок", "i": "🏠", "c": "obzory-tekhniki"}, {"s": "whirlpool-stiralnaya-instruktsiya-na-russkom", "t": "Инструкция Whirlpool на русском: поиск, расшифровка, коды", "i": "🏠", "c": "obzory-tekhniki"}, {"s": "whirlpool-green-generation-stiralnaya-mashina-instruktsiya", "t": "Whirlpool Green Generation: инструкция и руководство пользователя", "i": "🏠", "c": "obzory-tekhniki"}, {"s": "whirlpool-stiralnaya-mashina-oshibka-h2o", "t": "Ошибка H2O на стиральных машинах Whirlpool: причины и ремонт", "i": "⚠️", "c": "kody-oshibok"}, {"s": "whirlpool-stiralnaya-mashina-oshibka-e01", "t": "Ошибка E01 в стиральной машине Whirlpool: причины и ремонт", "i": "⚠️", "c": "kody-oshibok"}, {"s": "whirlpool-stiralnaya-mashina-s-vertikalnoj-instruktsiya", "t": "Whirlpool стиральная машина с вертикальной загрузкой: инструкция, коды", "i": "🏠", "c": "obzory-tekhniki"}, {"s": "whirlpool-stiralnaya-mashina-s-vertikalnoj-zagruzkoj-otzyvy", "t": "Whirlpool стиральная машина с вертикальной загрузкой: отзывы и анализ", "i": "🏠", "c": "obzory-tekhniki"}, {"s": "whirlpool-stiralnaya-mashina-instruktsiya-na-russkom", "t": "Whirlpool стиральная машина: инструкция на русском языке", "i": "🏠", "c": "obzory-tekhniki"}, {"s": "whirlpool-stiralnaya-mashina-vstraivaemaya", "t": "Встраиваемая стиральная машина Whirlpool: выбор, модели, монтаж", "i": "📁", "c": null}, {"s": "whirlpool-stiralnaya-mashina-gde-proizvodyat", "t": "Где производят стиральные машины Whirlpool: заводы и модели", "i": "🏠", "c": "obzory-tekhniki"}, {"s": "whirlpool-stiralnaya-mashina-6-kg", "t": "Whirlpool стиральная машина 6 кг: обзор, характеристики и советы", "i": "🏠", "c": "obzory-tekhniki"}, {"s": "whirlpool-oshibka-f23-v-stiralnoj-mashine", "t": "Whirlpool ошибка F23: причины, диагностика и ремонт", "i": "🔧", "c": "remont-stiralnykh-mashin"}, {"s": "whirpool-s-freshcare-stiralnaya-mashina", "t": "Стиральная машина Whirlpool с Fresh Care: функции и отзывы", "i": "🏠", "c": "obzory-tekhniki"}, {"s": "whirlpool-stiralnaya-mashina-otzyvy-o-tekhnike", "t": "Whirlpool стиральная машина: отзывы, обзоры и реальный опыт", "i": "🏠", "c": "obzory-tekhniki"}, {"s": "whirlpool-stiralnaya-mashina-s-vertikalnoj-zagruzkoj-instruktsiya-na-russkom-yazyke-s-foto", "t": "Whirlpool вертикальная стиральная машина: инструкция, коды, фото", "i": "🏠", "c": "obzory-tekhniki"}, {"s": "whirlpool-stiralnaya-mashina-kuda-sypat-poroshok", "t": "Whirlpool стиральная машина: куда сыпать порошок", "i": "✨", "c": "chistka-i-obsluzhivanie"}, {"s": "whirlpool-stiralnaya-mashina-kak-vklyuchit-stirku", "t": "Как включить стирку на Whirlpool: пошаговая инструкция", "i": "🏠", "c": "obzory-tekhniki"}, {"s": "whirlpool-stiralnaya-mashina-s-vertikalnoj-zagruzkoj-instruktsiya-na-russkom", "t": "Инструкция Whirlpool вертикальная загрузка: настройка и коды", "i": "🏠", "c": "obzory-tekhniki"}]